is_base_64/__init__.py
is_base_64/is_base_64.py
is_base_64-0.0.1.dist-info/METADATA
is_base_64-0.0.1.dist-info/WHEEL
is_base_64-0.0.1.dist-info/licenses/LICENSE
is_base_64-0.0.1.dist-info/RECORD
