Metadata-Version: 2.1
Name: is_base_64
Version: 0.0.1
Summary: Simple library for check the string is base64
Project-URL: Homepage, https://github.com/juunini/is-base-64-py
Project-URL: Bug Tracker, https://github.com/juunini/is-base-64-py/issues
Author-email: juunini <juuni.ni.i@gmail.com>
License-File: LICENSE
Classifier: License :: OSI Approved :: MIT License
Classifier: Operating System :: OS Independent
Classifier: Programming Language :: Python :: 3
Requires-Python: >=3.7
